{"type":"FeatureCollection","name":"Lake Forest Park_station_and_jurisdiction_data","crs":{"type":"name","properties":{"name":"urn:ogc:def:crs:OGC:1.3:CRS84"}},"features":[{"type":"Feature","properties":{"JURISDICTION_ID":"G53037270","STATION_ID":"STATION031"},"geometry":{"type":"Point","coordinates":[-122.28835,47.74107]}},{"type":"Feature","properties":{"JURISDICTION_ID":"G53037270","STATION_ID":"STATION034"},"geometry":{"type":"Point","coordinates":[-122.28483,47.74827]}},{"type":"Feature","properties":{"JURISDICTION_ID":"G53037270","STATION_ID":"STATION121"},"geometry":{"type":"Point","coordinates":[-122.27579,47.75381]}}]}