{"type":"FeatureCollection","name":"Kirkland_station_and_jurisdiction_data","crs":{"type":"name","properties":{"name":"urn:ogc:def:crs:OGC:1.3:CRS84"}},"features":[{"type":"Feature","properties":{"JURISDICTION_ID":"G53035940","STATION_ID":"STATION257"},"geometry":{"type":"Point","coordinates":[-122.18453,47.67919]}},{"type":"Feature","properties":{"JURISDICTION_ID":"G53035940","STATION_ID":"STATION397"},"geometry":{"type":"Point","coordinates":[-122.18742,47.71839]}}]}